odoo/addons/picking_very_high_priority/README.rst
odoo/addons/picking_very_high_priority/__init__.py
odoo/addons/picking_very_high_priority/__manifest__.py
odoo/addons/picking_very_high_priority/i18n/es.po
odoo/addons/picking_very_high_priority/models/__init__.py
odoo/addons/picking_very_high_priority/models/stock_move.py
odoo/addons/picking_very_high_priority/models/stock_picking.py
odoo/addons/picking_very_high_priority/static/description/icon.png
odoo14_addon_picking_very_high_priority-14.0.1.0.0.dist-info/METADATA
odoo14_addon_picking_very_high_priority-14.0.1.0.0.dist-info/WHEEL
odoo14_addon_picking_very_high_priority-14.0.1.0.0.dist-info/top_level.txt
odoo14_addon_picking_very_high_priority-14.0.1.0.0.dist-info/RECORD
